{
  "posts": [
    {
      "userId": 23,
      "title": "Testin Posts",
      "author": "nikola11@gmail.com",
      "post": "This is post testing bla bla",
      "id": 4
    },
    {
      "userId": 23,
      "title": "Another Testing Posts",
      "author": "nikola11@gmail.com",
      "post": "Testing Posts Bla Bla bla",
      "id": 5
    },
    {
      "userId": 23,
      "title": "New testing post",
      "author": "nikola11@gmail.com",
      "post": "sdfasdfasdfasdfasdfsdfsadfasdf",
      "id": 6
    },
    {
      "userId": 21,
      "title": "Post from another user",
      "author": "nikola30@gmail.com",
      "post": "asdfsdfasdf sdf asdfasdf asdfasdf sadf asdf asdfsd",
      "id": 20
    },
    {
      "userId": 25,
      "title": "asdfsdf",
      "post": "sdfasdfsadf",
      "id": 23
    },
    {
      "userId": 27,
      "author": "nikola12@gmail.com",
      "title": "sadfasdf",
      "post": "sdfasdfasd",
      "id": 24
    }
  ],
  "comments": [
    {
      "userId": 21,
      "authorId": 21,
      "postId": 20,
      "author": "nikola30@gmail.com",
      "comment": "my comment",
      "id": 5
    },
    {
      "userId": 25,
      "authorId": 27,
      "postId": 23,
      "author": "nikola12@gmail.com",
      "comment": "asdfsdfsadfasdf",
      "id": 11
    },
    {
      "id": 12,
      "userId": 27,
      "authorId": 28,
      "postId": 24,
      "author": "nikola99@gmail.com",
      "comment": "asdfasdfasdfs sdf sdfasdf "
    },
    {
      "id": 13,
      "userId": 25,
      "authorId": 23,
      "postId": 23,
      "author": "nikola11@gmail.com",
      "comment": "sfasdfsdaf sdfasdfasd fasdfasdf"
    },
    {
      "userId": 27,
      "authorId": 23,
      "postId": 24,
      "author": "nikola11@gmail.com",
      "comment": "asdfasdfasdf",
      "id": 14
    },
    {
      "userId": 27,
      "authorId": 23,
      "postId": 24,
      "author": "nikola11@gmail.com",
      "comment": "sdfsdfsdfsdaf",
      "id": 15
    },
    {
      "userId": 27,
      "authorId": 23,
      "postId": 24,
      "author": "nikola11@gmail.com",
      "comment": "ssdfsdfsdaf",
      "id": 16
    },
    {
      "userId": 27,
      "authorId": 23,
      "postId": 24,
      "author": "nikola11@gmail.com",
      "comment": "sdgdfgsdf",
      "id": 17
    }
  ],
  "profile": {
    "name": "typicode"
  },
  "users": [
    {
      "email": "nikola",
      "password": "123321",
      "id": 2
    },
    {
      "id": 3
    },
    {
      "id": 4
    },
    {
      "id": 5
    },
    {
      "id": 6
    },
    {
      "id": 7
    },
    {
      "email": "nikola@pass.com",
      "password": "123456",
      "id": 8
    },
    {
      "email": "user55@bla.com",
      "password": "1423321",
      "id": 9
    },
    {
      "email": "nikola@sdfsf.com",
      "password": "158654",
      "id": 10
    },
    {
      "email": "nikola@test.com",
      "password": "123321",
      "id": 11
    },
    {
      "email": "nikola@test2.com",
      "password": "123456",
      "id": 12
    },
    {
      "email": "nikola5@test.com",
      "password": "123456",
      "id": 13
    },
    {
      "email": "nikola6@test.com",
      "password": "123456",
      "id": 14
    },
    {
      "email": "nikola@bla.com",
      "password": "123456",
      "id": 15
    },
    {
      "email": "nikola55@bla.com",
      "password": "123456",
      "id": 16
    },
    {
      "email": "nikola@gmao.com",
      "password": "123456",
      "id": 17
    },
    {
      "email": "nikola18@test.com",
      "password": "123456",
      "id": 18
    },
    {
      "email": "nikola19@gmail.com",
      "password": "123456",
      "id": 19
    },
    {
      "email": "nikola20@gmail.com",
      "password": "123456",
      "id": 20
    },
    {
      "email": "nikola30@gmail.com",
      "password": "123456",
      "id": 21
    },
    {
      "email": "nikola@ssdfs.com",
      "password": "123321",
      "id": 22
    },
    {
      "email": "nikola11@gmail.com",
      "password": "123456",
      "id": 23
    },
    {
      "email": "nikola11@gmail.com",
      "password": "123456",
      "id": 24
    },
    {
      "payload": {
        "email": "nikola12@gmail.com",
        "password": "123456"
      },
      "id": 25
    },
    {
      "payload": {
        "email": "nikola12@gmail.com",
        "password": "123456"
      },
      "id": 26
    },
    {
      "email": "nikola12@gmail.com",
      "password": "123456",
      "id": 27
    },
    {
      "email": "nikola99@gmail.com",
      "password": "123456",
      "id": 28
    },
    {
      "email": "testingReg@gmail.com",
      "password": "123456",
      "id": 29
    }
  ]
}